switchboard/__init__.py
switchboard/base.py
switchboard/builtins.py
switchboard/conditions.py
switchboard/decorators.py
switchboard/helpers.py
switchboard/manager.py
switchboard/middleware.py
switchboard/models.py
switchboard/proxy.py
switchboard/settings.py
switchboard/signals.py
switchboard/template_helpers.py
switchboard/testutils.py
switchboard/admin/__init__.py
switchboard/admin/index.tpl
switchboard/admin/utils.py
switchboard/admin/templates/__init__.py
switchboard/tests/__init__.py
switchboard/tests/test_base.py
switchboard/tests/test_builtins.py
switchboard/tests/test_conditions.py
switchboard/tests/test_decorators.py
switchboard/tests/test_manager.py
switchboard/tests/test_middleware.py
switchboard/tests/test_models.py
switchboard/tests/test_testutils.py
switchboard/tests/admin/__init__.py
switchboard/tests/admin/test_utils.py
switchboard-1.6.9.dist-info/licenses/LICENSE
switchboard-1.6.9.dist-info/METADATA
switchboard-1.6.9.dist-info/WHEEL
switchboard-1.6.9.dist-info/top_level.txt
switchboard-1.6.9.dist-info/RECORD
