Metadata-Version: 2.4
Name: switchboard
Version: 1.6.9
Summary: Feature flipper for Pyramid, Pylons, or TurboGears apps.
Home-page: https://github.com/switchboardpy/switchboard/
Download-URL: https://github.com/switchboardpy/switchboard/releases
Author: Kyle Adams
Author-email: kadams54@users.noreply.github.com
License: Apache License
Keywords: switches feature flipper pyramid pylons turbogears
Classifier: Programming Language :: Python
Classifier: Programming Language :: Python :: 3
Classifier: Programming Language :: Python :: 3.9
Classifier: Programming Language :: Python :: 3.10
Classifier: Programming Language :: Python :: 3.11
Classifier: Programming Language :: Python :: 3.12
Classifier: Programming Language :: Python :: 3.13
Classifier: Topic :: Software Development :: Libraries :: Python Modules
Requires-Python: >=3.9
License-File: LICENSE
Requires-Dist: pymongo>=3
Requires-Dist: blinker>=1.2
Requires-Dist: WebOb>=0.9
Requires-Dist: Mako>=0.9
Requires-Dist: bottle>=0.12.8
Dynamic: author
Dynamic: author-email
Dynamic: classifier
Dynamic: description
Dynamic: description-content-type
Dynamic: download-url
Dynamic: home-page
Dynamic: keywords
Dynamic: license
Dynamic: license-file
Dynamic: requires-dist
Dynamic: requires-python
Dynamic: summary
